.gitignore
.pre-commit-config.yaml
LICENSE
MANIFEST.in
README.md
setup.cfg
setup.py
www.superformosa.nl.png
bin/photog
photog/__init__.py
photog/template.html
photog.egg-info/PKG-INFO
photog.egg-info/SOURCES.txt
photog.egg-info/dependency_links.txt
photog.egg-info/requires.txt
photog.egg-info/top_level.txt
photog/__pycache__/__init__.cpython-310.pyc
photog/static/SourceSansPro-ExtraLight.woff
photog/static/jquery-3.6.0.min.js
photog/static/main.css
photog/static/photoswipe.js
photog/static/superformosa.js
photog/static/photoswipe/photoswipe-ui-default.js
photog/static/photoswipe/photoswipe.css
photog/static/photoswipe/photoswipe.js
photog/static/photoswipe/default-skin/default-skin.css
photog/static/photoswipe/default-skin/default-skin.png
photog/static/photoswipe/default-skin/default-skin.svg
photog/static/photoswipe/default-skin/preloader.gif