Metadata-Version: 2.1
Name: photog
Version: 3.0.0
Summary: Static photography website generator
Home-page: https://github.com/rtts/photog
Author: Jaap Joris Vens
Author-email: photog@jj.rtts.eu
License: AGPL3
Platform: UNKNOWN
Classifier: Programming Language :: Python :: 3
Classifier: License :: OSI Approved :: GNU Affero General Public License v3 or later (AGPLv3+)
Classifier: Operating System :: OS Independent
License-File: LICENSE
